LICENSE
README.md
setup.py
keymorph/__init__.py
keymorph/augmentation.py
keymorph/keypoint_aligners.py
keymorph/layers.py
keymorph/loss_ops.py
keymorph/model.py
keymorph/net.py
keymorph/utils.py
keymorph/viz_tools.py
keymorph.egg-info/PKG-INFO
keymorph.egg-info/SOURCES.txt
keymorph.egg-info/dependency_links.txt
keymorph.egg-info/requires.txt
keymorph.egg-info/top_level.txt
keymorph/unet3d/__init__.py
keymorph/unet3d/buildingblocks.py
keymorph/unet3d/config.py
keymorph/unet3d/losses.py
keymorph/unet3d/metrics.py
keymorph/unet3d/model.py
keymorph/unet3d/predictor.py
keymorph/unet3d/se.py
keymorph/unet3d/seg_metrics.py
keymorph/unet3d/trainer.py
keymorph/unet3d/utils.py
test/__init__.py
test/test.py